BigQueryUtils/__init__.py
BigQueryUtils/bqutils.py
DateUtils/__init__.py
DateUtils/date_utils.py
Logger/__init__.py
Logger/logger.py
MailSender/__init__.py
MailSender/mail_sender.py
fp_th_di/__init__.py
fp_th_di/bqutils.py
fp_th_di/date_utils.py
fp_th_di/file_utilities.py
fp_th_di/google_drive_utils.py
fp_th_di/google_secret_manager.py
fp_th_di/google_storage_manager.py
fp_th_di/logger.py
fp_th_di/mail_sender.py
fp_th_di/mime_types.py
fp_th_di/sftputils.py
fp_th_di/slackutils.py
fp_th_di/mail_box/__init__.py
fp_th_di/mail_box/email_attachment.py
fp_th_di/mail_box/email_object.py
fp_th_di/mail_box/mail_box.py
fp_th_di-3.0.4.dist-info/METADATA
fp_th_di-3.0.4.dist-info/WHEEL
fp_th_di-3.0.4.dist-info/top_level.txt
fp_th_di-3.0.4.dist-info/RECORD
