Metadata-Version: 2.1
Name: fp-th-di
Version: 3.0.4
Summary: Foodpanda Thailand Data & Insight team utility functions
Author: Mathara Rojanamontien
Author-email: mathara.rojanamontien@foodpanda.co.th
License: Delivery Hero (Thailand) Co., Ltd.
Classifier: Programming Language :: Python :: 3
